infraforge_installer/__init__.py
infraforge_installer/main.py
infraforge_installer-0.1.1.dist-info/licenses/LICENSE
infraforge_installer-0.1.1.dist-info/METADATA
infraforge_installer-0.1.1.dist-info/WHEEL
infraforge_installer-0.1.1.dist-info/entry_points.txt
infraforge_installer-0.1.1.dist-info/top_level.txt
infraforge_installer-0.1.1.dist-info/RECORD
