Metadata-Version: 2.4
Name: infraforge-installer
Version: 0.1.1
Summary: InfraForge system installer (installer-only, runtime untouched)
Requires-Python: >=3.8
License-File: LICENSE
Dynamic: license-file
